setup.py
turihub/__init__.py
turihub.egg-info/PKG-INFO
turihub.egg-info/SOURCES.txt
turihub.egg-info/dependency_links.txt
turihub.egg-info/top_level.txt