Metadata-Version: 2.2
Name: turihub
Version: 0.0.1.dev0
Summary: Example package
Classifier: Programming Language :: Python :: 3
Classifier: License :: OSI Approved :: MIT License
Classifier: Operating System :: OS Independent
Dynamic: classifier
Dynamic: summary
